aws_solutions_konstruk/aws_iot_kinesisfirehose_s3/__init__.py
aws_solutions_konstruk/aws_iot_kinesisfirehose_s3/py.typed
aws_solutions_konstruk/aws_iot_kinesisfirehose_s3/_jsii/__init__.py
aws_solutions_konstruk/aws_iot_kinesisfirehose_s3/_jsii/aws-iot-kinesisfirehose-s3@0.8.1.jsii.tgz
aws_solutions_konstruk.aws_iot_kinesisfirehose_s3-0.8.1.dist-info/METADATA
aws_solutions_konstruk.aws_iot_kinesisfirehose_s3-0.8.1.dist-info/WHEEL
aws_solutions_konstruk.aws_iot_kinesisfirehose_s3-0.8.1.dist-info/top_level.txt
aws_solutions_konstruk.aws_iot_kinesisfirehose_s3-0.8.1.dist-info/RECORD
