Metadata-Version: 2.1
Name: aws-solutions-konstruk.aws-iot-kinesisfirehose-s3
Version: 0.8.1
Summary: CDK Constructs for AWS IoT to AWS Kinesis Firehose to AWS S3 integration.
Home-page: https://github.com/awslabs/aws-solutions-konstruk.git
Author: Amazon Web Services
License: Apache-2.0
Project-URL: Source, https://github.com/awslabs/aws-solutions-konstruk.git
Platform: UNKNOWN
Classifier: Intended Audience :: Developers
Classifier: Operating System :: OS Independent
Classifier: Programming Language :: JavaScript
Classifier: Programming Language :: Python :: 3 :: Only
Classifier: Programming Language :: Python :: 3.6
Classifier: Programming Language :: Python :: 3.7
Classifier: Programming Language :: Python :: 3.8
Classifier: Typing :: Typed
Classifier: License :: OSI Approved
Requires-Python: >=3.6
Requires-Dist: jsii (<2.0.0,>=1.5.0)
Requires-Dist: publication (>=0.0.3)
Requires-Dist: aws-cdk.aws-iam (<1.41.0,>=1.40.0)
Requires-Dist: aws-cdk.aws-iot (<1.41.0,>=1.40.0)
Requires-Dist: aws-cdk.aws-kinesisfirehose (<1.41.0,>=1.40.0)
Requires-Dist: aws-cdk.aws-s3 (<1.41.0,>=1.40.0)
Requires-Dist: aws-cdk.core (<1.41.0,>=1.40.0)
Requires-Dist: aws-solutions-konstruk.aws-kinesis-firehose-s3 (<0.9.0,>=0.8.1)
Requires-Dist: aws-solutions-konstruk.core (<0.9.0,>=0.8.1)
Requires-Dist: constructs (<4.0.0,>=3.0.2)
